multiplanet/__init__.py
multiplanet/mpstatus.py
multiplanet/multiplanet.py
multiplanet/multiplanet_module.py
multiplanet/multiplanet_version.py
multiplanet-2.0.3.dist-info/LICENSE
multiplanet-2.0.3.dist-info/METADATA
multiplanet-2.0.3.dist-info/WHEEL
multiplanet-2.0.3.dist-info/entry_points.txt
multiplanet-2.0.3.dist-info/top_level.txt
multiplanet-2.0.3.dist-info/RECORD
