Metadata-Version: 2.1
Name: multiplanet
Version: 2.0.3
Summary: VPLANET parameter sweep helper
Home-page: https://github.com/VirtualPlanetaryLaboratory/multi-planet
Author: Caitlyn Wilhelm
Author-email: cwilhelm@uw.edu
License: MIT
License-File: LICENSE
Requires-Dist: numpy
Requires-Dist: h5py
Requires-Dist: argparse
Requires-Dist: pandas
Requires-Dist: scipy
Requires-Dist: vspace
Requires-Dist: bigplanet
